src/__init__.py
src/main.py
natchecker-0.2.1.dist-info/METADATA
natchecker-0.2.1.dist-info/WHEEL
natchecker-0.2.1.dist-info/entry_points.txt
natchecker-0.2.1.dist-info/top_level.txt
natchecker-0.2.1.dist-info/RECORD
